LICENSE
MANIFEST.in
README.md
README.txt
setup.py
OASYS1_Elettra_Extensions.egg-info/PKG-INFO
OASYS1_Elettra_Extensions.egg-info/SOURCES.txt
OASYS1_Elettra_Extensions.egg-info/dependency_links.txt
OASYS1_Elettra_Extensions.egg-info/entry_points.txt
OASYS1_Elettra_Extensions.egg-info/namespace_packages.txt
OASYS1_Elettra_Extensions.egg-info/not-zip-safe
OASYS1_Elettra_Extensions.egg-info/requires.txt
OASYS1_Elettra_Extensions.egg-info/top_level.txt
orangecontrib/__init__.py
orangecontrib/elettra/__init__.py
orangecontrib/elettra/menu/__init__.py
orangecontrib/elettra/shadow/__init__.py
orangecontrib/elettra/shadow/util/__init__.py
orangecontrib/elettra/shadow/widgets/__init__.py
orangecontrib/elettra/shadow/widgets/extension/__init__.py
orangecontrib/elettra/shadow/widgets/extension/ow_fe_to_shadow.py
orangecontrib/elettra/shadow/widgets/extension/icons/LogoElettra_transparent.png
orangecontrib/elettra/shadow/widgets/extension/icons/flux.png
orangecontrib/elettra/shadow/widgets/extension/icons/flux_calculator.png
orangecontrib/elettra/shadow/widgets/extension/icons/thermal_load.png
orangecontrib/elettra/shadow/widgets/extension/misc/thermal_load_usage.png
orangecontrib/elettra/srw/__init__.py
orangecontrib/elettra/srw/util/__init__.py
orangecontrib/elettra/srw/widgets/__init__.py
orangecontrib/elettra/srw/widgets/extension/__init__.py
orangecontrib/elettra/srw/widgets/extension/icons/LogoElettra_transparent.png
orangecontrib/elettra/syned/__init__.py
orangecontrib/elettra/syned/data/Elettra_Long_Straight.json
orangecontrib/elettra/syned/data/Elettra_Short_Straight.json
orangecontrib/elettra/syned/data/__init__.py
orangecontrib/elettra/syned/data/elettra2_sources.csv
orangecontrib/elettra/syned/data/__pycache__/__init__.cpython-38.pyc
orangecontrib/elettra/syned/util/__init__.py
orangecontrib/elettra/syned/widgets/__init__.py
orangecontrib/elettra/syned/widgets/extension/__init__.py
orangecontrib/elettra/syned/widgets/extension/ow_elettra2.py
orangecontrib/elettra/syned/widgets/extension/icons/LogoElettra_transparent.png
orangecontrib/elettra/syned/widgets/extension/icons/elettra_source.png
orangecontrib/elettra/util/__init__.py
orangecontrib/elettra/util/elettra_util.py
orangecontrib/elettra/util/gui/__init__.py
orangecontrib/elettra/util/gui/ow_abstract_thermal_load_converter.py
orangecontrib/elettra/wofry/__init__.py
