Metadata-Version: 2.1
Name: OASYS1-Elettra-Extensions
Version: 0.2.72
Summary: OASYS extensions for Elettra
Home-page: https://github.com/oasys-elettra-kit/OASYS1-ELETTRA-Extensions
Download-URL: https://github.com/oasys-elettra-kit/OASYS1-ELETTRA-Extensions
Author: Aljosa Hafner
Author-email: aljosa.hafner@ceric-eric.eu
License: GPLv3
Keywords: raytracing,simulator,oasys1
Classifier: Development Status :: 4 - Beta
Classifier: Environment :: X11 Applications :: Qt
Classifier: Environment :: Console
Classifier: Environment :: Plugins
Classifier: Programming Language :: Python :: 3
Classifier: Intended Audience :: Science/Research
License-File: LICENSE
Requires-Dist: setuptools
Requires-Dist: pandas
